website_ui/__init__.py
website_ui/admin.py
website_ui/apps.py
website_ui/models.py
website_ui/tests.py
website_ui/views.py
website_ui/migrations/__init__.py
website_ui/static/css/nucleo-icons.css
website_ui/static/css/nucleo-svg.css
website_ui/static/css/soft-design-system.css
website_ui/static/css/soft-design-system.css.map
website_ui/static/css/soft-design-system.min.css
website_ui/static/fonts/nucleo-icons.eot
website_ui/static/fonts/nucleo-icons.svg
website_ui/static/fonts/nucleo-icons.ttf
website_ui/static/fonts/nucleo-icons.woff
website_ui/static/fonts/nucleo-icons.woff2
website_ui/static/fonts/nucleo.eot
website_ui/static/fonts/nucleo.ttf
website_ui/static/fonts/nucleo.woff
website_ui/static/fonts/nucleo.woff2
website_ui/static/img/anastasia.jpg
website_ui/static/img/annie-spratt.jpg
website_ui/static/img/apple-icon.png
website_ui/static/img/blog7-1.jpg
website_ui/static/img/blog7-2.jpg
website_ui/static/img/blog7-3.jpg
website_ui/static/img/brooke.jpg
website_ui/static/img/bruce-mars.jpg
website_ui/static/img/card-2.jpg
website_ui/static/img/card-3.jpg
website_ui/static/img/charles.jpg
website_ui/static/img/down-arrow-dark.svg
website_ui/static/img/down-arrow-white.svg
website_ui/static/img/down-arrow.svg
website_ui/static/img/favicon.png
website_ui/static/img/ivana-square.jpg
website_ui/static/img/ivana.jpg
website_ui/static/img/ivancik.jpg
website_ui/static/img/jordan.jpg
website_ui/static/img/kal-visuals-square.jpg
website_ui/static/img/kal-visuals.jpg
website_ui/static/img/marie.jpg
website_ui/static/img/meeting.jpg
website_ui/static/img/nastuh.jpg
website_ui/static/img/office-dark.jpg
website_ui/static/img/team-1.jpg
website_ui/static/img/team-2.jpg
website_ui/static/img/team-3.jpg
website_ui/static/img/team-4.jpg
website_ui/static/img/toa-heftiba.jpg
website_ui/static/img/wave-1.svg
website_ui/static/img/curved-images/curved-10.jpg
website_ui/static/img/curved-images/curved-11.jpg
website_ui/static/img/curved-images/curved-6.jpg
django_template_website_ui-0.1.6.dist-info/LICENSE
django_template_website_ui-0.1.6.dist-info/METADATA
django_template_website_ui-0.1.6.dist-info/WHEEL
django_template_website_ui-0.1.6.dist-info/top_level.txt
django_template_website_ui-0.1.6.dist-info/RECORD
