Metadata-Version: 2.1
Name: django-template-website-ui
Version: 0.1.6
Summary: A Website UI Based On Django Template.
Author-email: Micro Enjoy <fuqiang.work@foxamil.com>
License: 
Project-URL: Homepage, https://github.com/django-libraries/django-template-website-ui
Project-URL: Documentation, https://github.com/django-libraries/django-template-website-ui
Project-URL: IssueTracker, https://github.com/django-libraries/django-template-website-ui/issues
Project-URL: Source, https://github.com/django-libraries/django-template-website-ui
License-File: LICENSE
Requires-Dist: Django >=3.0
